mysql_compressed_fields/__init__.py
mysql_compressed_fields/fields.py
mysql_compressed_fields/functions.py
django_mysql_compressed_fields-1.2.0.dist-info/LICENSE
django_mysql_compressed_fields-1.2.0.dist-info/WHEEL
django_mysql_compressed_fields-1.2.0.dist-info/METADATA
django_mysql_compressed_fields-1.2.0.dist-info/RECORD
