Metadata-Version: 2.1
Name: django-mysql-compressed-fields
Version: 1.2.0
Summary: A large text field, stored compressed in the database, for Django and MySQL.
Home-page: https://github.com/techsmartkids/django-mysql-compressed-fields
License: MIT
Author: David Foster
Author-email: david.foster@techsmart.codes
Requires-Python: >=3.9,<4.0
Classifier: Development Status :: 5 - Production/Stable
Classifier: Framework :: Django
Classifier: Intended Audience :: Developers
Classifier: License :: OSI Approved :: MIT License
Classifier: Programming Language :: Python :: 3
Classifier: Programming Language :: Python :: 3.9
Classifier: Programming Language :: Python :: 3.10
Classifier: Programming Language :: Python :: 3.11
Classifier: Programming Language :: Python :: 3
Classifier: Programming Language :: Python :: 3.10
Classifier: Programming Language :: Python :: 3.11
Classifier: Programming Language :: Python :: 3.9
Classifier: Topic :: Database
Classifier: Topic :: Internet
Classifier: Topic :: Software Development :: Libraries
Project-URL: Repository, https://github.com/techsmartkids/django-mysql-compressed-fields
Project-URL: Release notes, https://github.com/techsmartkids/django-mysql-compressed-fields/tree/main#release-notes
